flowui/__init__.py
flowui/base_operator.py
flowui/cli.py
flowui/logger.py
flowui/operator_generator.py
flowui/version.py
flowui/client/__init__.py
flowui/client/airflow_client.py
flowui/client/fs_client.py
flowui/client/github_rest_client.py
flowui/client/local_files_client.py
flowui/client/s3_client.py
flowui/example_repository/__init__.py
flowui/exceptions/__init__.py
flowui/exceptions/exceptions.py
flowui/operators/__init__.py
flowui/operators/bash_operator.py
flowui/operators/python_operator.py
flowui/schemas/__init__.py
flowui/schemas/from_upstream.py
flowui/schemas/operator_metadata.py
flowui/scripts/__init__.py
flowui/scripts/build_docker_images_operators.py
flowui/scripts/create_docker_compose_file.py
flowui/scripts/docker_compose_constants.py
flowui/scripts/docker_compose_scripts.py
flowui/scripts/generate_infrasctructure.py
flowui/scripts/load_operator.py
flowui/scripts/run_operator_bash.py
flowui/scripts/run_operator_docker.py
flowui/tasks/__init__.py
flowui/tasks/aws_batch_task.py
flowui/tasks/python_task.py
flowui/tasks/task.py
flowui/utils/__init__.py
flowui/utils/custom_types.py
flowui/utils/enum_types.py
flowui/utils/metadata_default.py
flowui/utils/validators.py
flowui_project-0.0.3.dist-info/METADATA
flowui_project-0.0.3.dist-info/WHEEL
flowui_project-0.0.3.dist-info/entry_points.txt
flowui_project-0.0.3.dist-info/top_level.txt
flowui_project-0.0.3.dist-info/RECORD
