Metadata-Version: 2.1
Name: flowui-project
Version: 0.0.3
Summary: FlowUI project
Author: Luiz Tauffer and Vinicius Vaz
Author-email: luiz@taufferconsulting.com
Keywords: airflow,UI
Requires-Python: >=3.7
Requires-Dist: apache-airflow (>=2.2.0)
Requires-Dist: apache-airflow-providers-amazon (==4.0.0)
Requires-Dist: apache-airflow-providers-docker (==3.0.0)
Requires-Dist: pydantic (==1.9.1)
Requires-Dist: docker (==5.0.3)
Requires-Dist: python-on-whales (==0.47.0)
Requires-Dist: boto3
Requires-Dist: dateparser
Requires-Dist: tomli (==2.0.1)
Requires-Dist: tomli-w (==1.0.0)
